LastFrame/__init__.py
LastFrame/__main__.py
LastFrame/cli.py
lastframe-1.0.1.dist-info/METADATA
lastframe-1.0.1.dist-info/WHEEL
lastframe-1.0.1.dist-info/entry_points.txt
lastframe-1.0.1.dist-info/top_level.txt
lastframe-1.0.1.dist-info/RECORD
