Metadata-Version: 2.4
Name: LastFrame
Version: 1.0.1
Summary: LastFrame is a simple command-line tool for extracting the last frame from MP4 video files using OpenCV (cv2)
Author-email: Wilgat Wong <wilgat.wong@gmail.com>
License: MIT
Project-URL: Homepage, https://github.com/Wilgat/LastFrame
Project-URL: Repository, https://github.com/Wilgat/LastFrame
Project-URL: Issues, https://github.com/Wilgat/LastFrame/issues
Keywords: logging,sudo,chronicle,example
Requires-Python: !=3.0.*,!=3.1.*,!=3.2.*,!=3.3.*,!=3.4.*,>=2.7
Requires-Dist: ChronicleLogger>=1.2.3
Requires-Dist: opencv-python
